elektropy/__init__.py
elektropy/circuits/basic_functions.py
elektropy/circuits/mesh_current.py
elektropy/circuits/node_voltage.py
elektropy/circuits/resistance.py
elektropy/circuits/thevenin_norton.py
elektropy/digitals/binary.py
elektropy/digitals/simplify_logic.py
elektropy/digitals/truth_table.py
elektropy/sensory/pt100.py
elektropy/sensory/wheatstone.py
elektropy-0.1.2.dist-info/licenses/LICENSE
elektropy-0.1.2.dist-info/METADATA
elektropy-0.1.2.dist-info/WHEEL
elektropy-0.1.2.dist-info/top_level.txt
elektropy-0.1.2.dist-info/RECORD
