Metadata-Version: 2.4
Name: elektropy
Version: 0.1.2
Summary: A Python library for circuit and digital electronics solving.
Author-email: Daniel Olsen <184446@stud.hvl.no>
License: MIT
Project-URL: Homepage, https://github.com/danielols3n/elektropy
Project-URL: Issues, https://github.com/danielols3n/elektropy/issues
Requires-Python: >=3.8
License-File: LICENSE
Requires-Dist: numpy
Requires-Dist: sympy>=1.12
Dynamic: license-file
